rebnypy/__init__.py
rebnypy/client.py
rebnypy/lookups.py
rebnypy-1.0.1.dist-info/DESCRIPTION.rst
rebnypy-1.0.1.dist-info/METADATA
rebnypy-1.0.1.dist-info/RECORD
rebnypy-1.0.1.dist-info/WHEEL
rebnypy-1.0.1.dist-info/metadata.json
rebnypy-1.0.1.dist-info/top_level.txt
