Metadata-Version: 2.0
Name: rebnypy
Version: 1.0.1
Summary: A Python library for interacting with the REBNY listing service
Home-page: https://github.com/RealGeeks/rebnypy
Author: Kevin McCarthy
Author-email: me@kevinmccarthy.org
License: MIT
Platform: UNKNOWN
Classifier: Environment :: Console
Classifier: Intended Audience :: Developers
Classifier: Programming Language :: Python
Classifier: License :: OSI Approved :: MIT License
Requires-Dist: requests
